split_python4gpt/__init__.py
split_python4gpt/__main__.py
split_python4gpt/minifier.py
split_python4gpt-1.0.3.dist-info/LICENSE.txt
split_python4gpt-1.0.3.dist-info/METADATA
split_python4gpt-1.0.3.dist-info/WHEEL
split_python4gpt-1.0.3.dist-info/entry_points.txt
split_python4gpt-1.0.3.dist-info/top_level.txt
split_python4gpt-1.0.3.dist-info/RECORD
