Metadata-Version: 2.1
Name: split-python4gpt
Version: 1.0.3
Summary: Python tool designed to reorganize large Python projects into minified files based on a specified token limit. This is particularly useful for processing large Python projects with GPT models, as it allows the models to handle the data in manageable chunks.
Home-page: https://github.com/twardoch/split-python4gpt
Author: Adam Twardoch
Author-email: adam+github@twardoch.com
License: Apache-2.0
Project-URL: Documentation, https://twardoch.github.io/split-python4gpt/
Project-URL: Source, https://github.com/twardoch/split-python4gpt
Keywords: python,code-summarization,openai,text-summarization,summarization,code-processing,gpt,data-preprocessing,openai-gpt,gpt-3,gpt-4,gpt-35-turbo,gpt-35-turbo-16k
Platform: any
Classifier: Development Status :: 4 - Beta
Classifier: Programming Language :: Python
Classifier: Programming Language :: Python :: 3
Classifier: Programming Language :: Python :: 3.10
Classifier: Intended Audience :: Developers
Classifier: Intended Audience :: Science/Research
Classifier: Topic :: Text Processing
Classifier: License :: OSI Approved :: Apache Software License
Classifier: Operating System :: OS Independent
Requires-Python: <3.11,>=3.10
License-File: LICENSE.txt
Requires-Dist: fire (>=0.5.0)
Requires-Dist: tiktoken (>=0.4.0)
Requires-Dist: python-minifier (>=2.9.0)
Requires-Dist: pytype (>=2023.6.16)
Provides-Extra: testing
Requires-Dist: setuptools ; extra == 'testing'
Requires-Dist: pytest ; extra == 'testing'
Requires-Dist: pytest-cov ; extra == 'testing'
